[{"rank": 1, "estate": "Rose Court", "estate_zh": "Rose Court", "estate_display": "Rose Court", "district": "Causeway Bay", "district_zh": "铜锣湾", "district_display": "铜锣湾", "region": "Hong Kong Island", "region_zh": "港岛", "price_fmt": "HK$35.00M", "rent_fmt": "HK$263,160", "rent_note": "2 个租盘每呎租金平均 × 面积 · 同区（每呎租金平均）", "rent_warning": true, "gross": "9.02%", "coc": "6.68%", "coc_stress": "5.61%", "ssd_warning": false, "grade": "A", "grade_label": "强力推荐", "score": "78.3", "url": "https://www.28hse.com/en/buy/apartment/property-3926854", "source_label": "28Hse", "building_age": null, "building_age_uncertain": false}, {"rank": 2, "estate": "东熹苑", "estate_zh": "东熹苑", "estate_display": "东熹苑", "district": "Sai Wan Ho", "district_zh": "西湾河", "district_display": "西湾河", "region": "Hong Kong Island", "region_zh": "港岛", "price_fmt": "HK$6.50M", "rent_fmt": "HK$49,361", "rent_note": "11 个租盘每呎租金平均 × 面积 · 同区（楼龄调整）", "rent_warning": true, "gross": "9.11%", "coc": "6.41%", "coc_stress": "5.35%", "ssd_warning": false, "grade": "A", "grade_label": "强力推荐", "score": "75.8", "url": "https://www.28hse.com/en/buy/apartment/property-3902383", "source_label": "28Hse", "building_age": 31, "building_age_uncertain": false}, {"rank": 3, "estate": "鯉安苑", "estate_zh": "鯉安苑", "estate_display": "鯉安苑", "district": "Lam Tin", "district_zh": "蓝田", "district_display": "蓝田", "region": "Kowloon", "region_zh": "九龙", "price_fmt": "HK$6.50M", "rent_fmt": "HK$45,567", "rent_note": "4 个租盘每呎租金平均 × 面积 · 同区（楼龄调整）", "rent_warning": true, "gross": "8.41%", "coc": "5.52%", "coc_stress": "4.46%", "ssd_warning": false, "grade": "A", "grade_label": "强力推荐", "score": "69.0", "url": "https://www.28hse.com/en/buy/apartment/property-3022602", "source_label": "28Hse", "building_age": 23, "building_age_uncertain": false}, {"rank": 4, "estate": "低层唐楼", "estate_zh": "低层唐楼", "estate_display": "低层唐楼", "district": "Kowloon City", "district_zh": "九龙城", "district_display": "九龙城", "region": "Kowloon", "region_zh": "九龙", "price_fmt": "HK$5.20M", "rent_fmt": "HK$36,953", "rent_note": "7 个租盘每呎租金平均 × 面积 · 同区（楼龄调整）", "rent_warning": true, "gross": "8.53%", "coc": "5.27%", "coc_stress": "4.21%", "ssd_warning": false, "grade": "A", "grade_label": "强力推荐", "score": "68.1", "url": "https://www.28hse.com/en/buy/apartment/property-3798060", "source_label": "28Hse", "building_age": 0, "building_age_uncertain": true}, {"rank": 5, "estate": "东骏苑", "estate_zh": "东骏苑", "estate_display": "东骏苑", "district": "Shau Kei Wan", "district_zh": "筲箕湾", "district_display": "筲箕湾", "region": "Hong Kong Island", "region_zh": "港岛", "price_fmt": "HK$6.00M", "rent_fmt": "HK$41,136", "rent_note": "4 个租盘每呎租金平均 × 面积 · 同区（楼龄调整）", "rent_warning": true, "gross": "8.23%", "coc": "5.19%", "coc_stress": "4.13%", "ssd_warning": false, "grade": "A", "grade_label": "强力推荐", "score": "67.2", "url": "https://www.28hse.com/en/buy/apartment/property-3919031", "source_label": "28Hse", "building_age": 32, "building_age_uncertain": false}, {"rank": 6, "estate": "东熹苑", "estate_zh": "东熹苑", "estate_display": "东熹苑", "district": "Sai Wan Ho", "district_zh": "西湾河", "district_display": "西湾河", "region": "Hong Kong Island", "region_zh": "港岛", "price_fmt": "HK$5.30M", "rent_fmt": "HK$36,051", "rent_note": "3 个租盘每呎租金平均 × 面积 · 同区（楼龄调整）", "rent_warning": true, "gross": "8.16%", "coc": "5.13%", "coc_stress": "4.07%", "ssd_warning": false, "grade": "A", "grade_label": "强力推荐", "score": "66.9", "url": "https://www.28hse.com/en/buy/apartment/property-3917301", "source_label": "28Hse", "building_age": 31, "building_age_uncertain": false}, {"rank": 7, "estate": "东蔚苑", "estate_zh": "东蔚苑", "estate_display": "东蔚苑", "district": "Sai Ying Pun", "district_zh": "西营盘", "district_display": "西营盘", "region": "Hong Kong Island", "region_zh": "港岛", "price_fmt": "HK$5.00M", "rent_fmt": "HK$30,031", "rent_note": "30 个租盘每呎租金平均 × 面积 · 同区（楼龄调整）", "rent_warning": false, "gross": "7.21%", "coc": "4.13%", "coc_stress": "3.08%", "ssd_warning": false, "grade": "A", "grade_label": "强力推荐", "score": "66.1", "url": "https://www.28hse.com/en/buy/apartment/property-3904881", "source_label": "28Hse", "building_age": 33, "building_age_uncertain": false}, {"rank": 8, "estate": "錦豐苑", "estate_zh": "錦豐苑", "estate_display": "錦豐苑", "district": "Ma On Shan", "district_zh": "马鞍山", "district_display": "马鞍山", "region": "New Territories", "region_zh": "新界", "price_fmt": "HK$5.18M", "rent_fmt": "HK$31,764", "rent_note": "16 个租盘每呎租金平均 × 面积 · 同区（楼龄调整）", "rent_warning": false, "gross": "7.36%", "coc": "3.73%", "coc_stress": "2.67%", "ssd_warning": false, "grade": "B", "grade_label": "值得买入", "score": "64.4", "url": "https://www.28hse.com/en/buy/apartment/property-3820553", "source_label": "28Hse", "building_age": 29, "building_age_uncertain": false}, {"rank": 9, "estate": "Mountain View Court", "estate_zh": "Mountain View Court", "estate_display": "Mountain View Court", "district": "Mid-Levels West", "district_zh": "中环半山", "district_display": "中环半山", "region": "New Territories", "region_zh": "新界", "price_fmt": "HK$7.80M", "rent_fmt": "HK$49,290", "rent_note": "12 个租盘每呎租金平均 × 面积 · 同区（每呎租金平均）", "rent_warning": false, "gross": "7.58%", "coc": "4.62%", "coc_stress": "3.56%", "ssd_warning": false, "grade": "A", "grade_label": "强力推荐", "score": "63.9", "url": "https://www.midland.com.hk/en/property/Hong-Kong-Island-Mid-Levels-West-Mountain-View-Court-Lower-Floor-Flat-B1-M100479990", "source_label": "美聯", "building_age": null, "building_age_uncertain": false}, {"rank": 10, "estate": "西貢头段", "estate_zh": "西貢头段", "estate_display": "西貢头段", "district": "Sai Kung", "district_zh": "西贡", "district_display": "西贡", "region": "New Territories", "region_zh": "新界", "price_fmt": "HK$12.50M", "rent_fmt": "HK$76,908", "rent_note": "25 个租盘每呎租金平均 × 面积 · 同区（每呎租金平均）", "rent_warning": false, "gross": "7.38%", "coc": "4.06%", "coc_stress": "2.99%", "ssd_warning": false, "grade": "A", "grade_label": "强力推荐", "score": "63.2", "url": "https://www.28hse.com/en/buy/apartment/property-3919028", "source_label": "28Hse", "building_age": null, "building_age_uncertain": false}, {"rank": 11, "estate": "新興大廈", "estate_zh": "新興大廈", "estate_display": "新興大廈", "district": "Mong Kok", "district_zh": "旺角", "district_display": "旺角", "region": "Kowloon", "region_zh": "九龙", "price_fmt": "HK$7.60M", "rent_fmt": "HK$48,799", "rent_note": "1 个租盘每呎租金平均 × 面积 · 同区（楼龄调整）", "rent_warning": false, "gross": "7.71%", "coc": "4.44%", "coc_stress": "3.38%", "ssd_warning": false, "grade": "A", "grade_label": "强力推荐", "score": "62.9", "url": "https://www.28hse.com/en/buy/apartment/property-3922295", "source_label": "28Hse", "building_age": 60, "building_age_uncertain": false}, {"rank": 12, "estate": "雅濤阁", "estate_zh": "雅濤阁", "estate_display": "雅濤阁", "district": "Aberdeen", "district_zh": "香港仔", "district_display": "香港仔", "region": "Hong Kong Island", "region_zh": "港岛", "price_fmt": "HK$5.90M", "rent_fmt": "HK$34,122", "rent_note": "23 个租盘每呎租金平均 × 面积 · 同区（楼龄调整）", "rent_warning": false, "gross": "6.94%", "coc": "3.81%", "coc_stress": "2.75%", "ssd_warning": false, "grade": "B", "grade_label": "值得买入", "score": "62.8", "url": "https://www.28hse.com/en/buy/apartment/property-3093759", "source_label": "28Hse", "building_age": 22, "building_age_uncertain": false}, {"rank": 13, "estate": "慈愛苑", "estate_zh": "慈愛苑", "estate_display": "慈愛苑", "district": "Wong Tai Sin", "district_zh": "黄大仙", "district_display": "黄大仙", "region": "Kowloon", "region_zh": "九龙", "price_fmt": "HK$5.30M", "rent_fmt": "HK$34,008", "rent_note": "1 个租盘每呎租金平均 × 面积 · 同区（楼龄调整）", "rent_warning": false, "gross": "7.70%", "coc": "4.44%", "coc_stress": "3.38%", "ssd_warning": false, "grade": "A", "grade_label": "强力推荐", "score": "62.7", "url": "https://www.28hse.com/en/buy/apartment/property-3646896", "source_label": "28Hse", "building_age": 25, "building_age_uncertain": false}, {"rank": 14, "estate": "翠嶺山莊", "estate_zh": "翠嶺山莊", "estate_display": "翠嶺山莊", "district": "Shatin", "district_zh": "沙田", "district_display": "沙田", "region": "New Territories", "region_zh": "新界", "price_fmt": "HK$7.90M", "rent_fmt": "HK$41,868", "rent_note": "24 个租盘每呎租金平均 × 面积 · 同区（楼龄调整）", "rent_warning": false, "gross": "6.36%", "coc": "2.82%", "coc_stress": "1.76%", "ssd_warning": false, "grade": "B", "grade_label": "值得买入", "score": "62.5", "url": "https://www.28hse.com/en/buy/apartment/property-3920734", "source_label": "28Hse", "building_age": 33, "building_age_uncertain": false}, {"rank": 15, "estate": "雅濤阁", "estate_zh": "雅濤阁", "estate_display": "雅濤阁", "district": "Aberdeen", "district_zh": "香港仔", "district_display": "香港仔", "region": "Hong Kong Island", "region_zh": "港岛", "price_fmt": "HK$5.88M", "rent_fmt": "HK$33,706", "rent_note": "23 个租盘每呎租金平均 × 面积 · 同区（楼龄调整）", "rent_warning": false, "gross": "6.88%", "coc": "3.73%", "coc_stress": "2.67%", "ssd_warning": false, "grade": "B", "grade_label": "值得买入", "score": "62.2", "url": "https://www.28hse.com/en/buy/apartment/property-3798619", "source_label": "28Hse", "building_age": 24, "building_age_uncertain": false}, {"rank": 16, "estate": "愉翠苑", "estate_zh": "愉翠苑", "estate_display": "愉翠苑", "district": "Shatin", "district_zh": "沙田", "district_display": "沙田", "region": "New Territories", "region_zh": "新界", "price_fmt": "HK$5.80M", "rent_fmt": "HK$30,614", "rent_note": "34 个租盘每呎租金平均 × 面积 · 同区（楼龄调整）", "rent_warning": false, "gross": "6.33%", "coc": "2.78%", "coc_stress": "1.72%", "ssd_warning": false, "grade": "B", "grade_label": "值得买入", "score": "62.2", "url": "https://www.28hse.com/en/buy/apartment/property-3920909", "source_label": "28Hse", "building_age": 25, "building_age_uncertain": false}, {"rank": 17, "estate": "Imperial Court", "estate_zh": "Imperial Court", "estate_display": "Imperial Court", "district": "Ho Man Tin", "district_zh": "何文田", "district_display": "何文田", "region": "Kowloon", "region_zh": "九龙", "price_fmt": "HK$6.30M", "rent_fmt": "HK$38,727", "rent_note": "2 个租盘每呎租金平均 × 面积 · 同区（每呎租金平均）", "rent_warning": false, "gross": "7.38%", "coc": "3.76%", "coc_stress": "2.70%", "ssd_warning": false, "grade": "B", "grade_label": "值得买入", "score": "61.4", "url": "https://www.midland.com.hk/en/property/Kowloon-Ho-Man-Tin-Imperial-Court-Lower-Floor-Flat-D-M200038887", "source_label": "美聯", "building_age": null, "building_age_uncertain": false}, {"rank": 18, "estate": "永安苑", "estate_zh": "永安苑", "estate_display": "永安苑", "district": "Tin Hau", "district_zh": "天后", "district_display": "天后", "region": "Hong Kong Island", "region_zh": "港岛", "price_fmt": "HK$5.08M", "rent_fmt": "HK$28,770", "rent_note": "21 个租盘每呎租金平均 × 面积 · 同区（楼龄调整）", "rent_warning": false, "gross": "6.80%", "coc": "3.48%", "coc_stress": "2.42%", "ssd_warning": false, "grade": "B", "grade_label": "值得买入", "score": "61.2", "url": "https://www.28hse.com/en/buy/apartment/property-3903409", "source_label": "28Hse", "building_age": 62, "building_age_uncertain": false}, {"rank": 19, "estate": "雅濤阁", "estate_zh": "雅濤阁", "estate_display": "雅濤阁", "district": "Aberdeen", "district_zh": "香港仔", "district_display": "香港仔", "region": "Hong Kong Island", "region_zh": "港岛", "price_fmt": "HK$6.00M", "rent_fmt": "HK$33,706", "rent_note": "23 个租盘每呎租金平均 × 面积 · 同区（楼龄调整）", "rent_warning": false, "gross": "6.74%", "coc": "3.57%", "coc_stress": "2.51%", "ssd_warning": false, "grade": "B", "grade_label": "值得买入", "score": "61.1", "url": "https://www.28hse.com/en/buy/apartment/property-3513754", "source_label": "28Hse", "building_age": 24, "building_age_uncertain": false}, {"rank": 20, "estate": "冠德苑", "estate_zh": "冠德苑", "estate_display": "冠德苑", "district": "Ho Man Tin", "district_zh": "何文田", "district_display": "何文田", "region": "Kowloon", "region_zh": "九龙", "price_fmt": "HK$6.18M", "rent_fmt": "HK$33,711", "rent_note": "38 个租盘每呎租金平均 × 面积 · 同区（楼龄调整）", "rent_warning": false, "gross": "6.55%", "coc": "3.03%", "coc_stress": "1.97%", "ssd_warning": false, "grade": "B", "grade_label": "值得买入", "score": "60.4", "url": "https://www.28hse.com/en/buy/apartment/property-3911680", "source_label": "28Hse", "building_age": 6, "building_age_uncertain": true}, {"rank": 21, "estate": "逸港居", "estate_zh": "逸港居", "estate_display": "逸港居", "district": "Aberdeen", "district_zh": "香港仔", "district_display": "香港仔", "region": "Hong Kong Island", "region_zh": "港岛", "price_fmt": "HK$6.00M", "rent_fmt": "HK$33,351", "rent_note": "23 个租盘每呎租金平均 × 面积 · 同区（楼龄调整）", "rent_warning": false, "gross": "6.67%", "coc": "3.48%", "coc_stress": "2.42%", "ssd_warning": false, "grade": "B", "grade_label": "值得买入", "score": "60.4", "url": "https://www.28hse.com/en/buy/apartment/property-3910707", "source_label": "28Hse", "building_age": 26, "building_age_uncertain": false}, {"rank": 22, "estate": "唐明苑", "estate_zh": "唐明苑", "estate_display": "唐明苑", "district": "Tseung Kwan O", "district_zh": "将军澳", "district_display": "将军澳", "region": "New Territories", "region_zh": "新界", "price_fmt": "HK$5.25M", "rent_fmt": "HK$27,956", "rent_note": "9 个租盘每呎租金平均 × 面积 · 同区（楼龄调整）", "rent_warning": false, "gross": "6.39%", "coc": "2.77%", "coc_stress": "1.71%", "ssd_warning": false, "grade": "B", "grade_label": "值得买入", "score": "60.4", "url": "https://www.28hse.com/en/buy/apartment/property-3862929", "source_label": "28Hse", "building_age": 23, "building_age_uncertain": false}, {"rank": 23, "estate": "Greenhill Villa", "estate_zh": "Greenhill Villa", "estate_display": "Greenhill Villa", "district": "Shatin", "district_zh": "沙田", "district_display": "沙田", "region": "New Territories", "region_zh": "新界", "price_fmt": "HK$5.48M", "rent_fmt": "HK$27,572", "rent_note": "28 个租盘每呎租金平均 × 面积 · 同区（楼龄调整）", "rent_warning": false, "gross": "6.04%", "coc": "2.44%", "coc_stress": "1.38%", "ssd_warning": false, "grade": "B", "grade_label": "值得买入", "score": "59.7", "url": "https://www.28hse.com/en/buy/apartment/property-3928258", "source_label": "28Hse", "building_age": 6, "building_age_uncertain": true}, {"rank": 24, "estate": "冠德苑", "estate_zh": "冠德苑", "estate_display": "冠德苑", "district": "Ho Man Tin", "district_zh": "何文田", "district_display": "何文田", "region": "Kowloon", "region_zh": "九龙", "price_fmt": "HK$6.28M", "rent_fmt": "HK$33,711", "rent_note": "38 个租盘每呎租金平均 × 面积 · 同区（楼龄调整）", "rent_warning": false, "gross": "6.44%", "coc": "2.91%", "coc_stress": "1.85%", "ssd_warning": false, "grade": "B", "grade_label": "值得买入", "score": "59.6", "url": "https://www.28hse.com/en/buy/apartment/property-3773519", "source_label": "28Hse", "building_age": 6, "building_age_uncertain": true}, {"rank": 25, "estate": "东熹苑", "estate_zh": "东熹苑", "estate_display": "东熹苑", "district": "Sai Wan Ho", "district_zh": "西湾河", "district_display": "西湾河", "region": "Hong Kong Island", "region_zh": "港岛", "price_fmt": "HK$5.98M", "rent_fmt": "HK$34,088", "rent_note": "15 个租盘每呎租金平均 × 面积 · 同区（楼龄调整）", "rent_warning": false, "gross": "6.84%", "coc": "3.64%", "coc_stress": "2.58%", "ssd_warning": false, "grade": "B", "grade_label": "值得买入", "score": "59.1", "url": "https://www.28hse.com/en/buy/apartment/property-3890354", "source_label": "28Hse", "building_age": 30, "building_age_uncertain": false}, {"rank": 26, "estate": "永安苑", "estate_zh": "永安苑", "estate_display": "永安苑", "district": "Tin Hau", "district_zh": "天后", "district_display": "天后", "region": "Hong Kong Island", "region_zh": "港岛", "price_fmt": "HK$5.28M", "rent_fmt": "HK$28,770", "rent_note": "21 个租盘每呎租金平均 × 面积 · 同区（楼龄调整）", "rent_warning": false, "gross": "6.54%", "coc": "3.18%", "coc_stress": "2.13%", "ssd_warning": false, "grade": "B", "grade_label": "值得买入", "score": "59.0", "url": "https://www.28hse.com/en/buy/apartment/property-3882862", "source_label": "28Hse", "building_age": 62, "building_age_uncertain": false}, {"rank": 27, "estate": "唐明苑", "estate_zh": "唐明苑", "estate_display": "唐明苑", "district": "Tseung Kwan O", "district_zh": "将军澳", "district_display": "将军澳", "region": "New Territories", "region_zh": "新界", "price_fmt": "HK$6.50M", "rent_fmt": "HK$32,857", "rent_note": "17 个租盘每呎租金平均 × 面积 · 同区（楼龄调整）", "rent_warning": false, "gross": "6.07%", "coc": "2.31%", "coc_stress": "1.25%", "ssd_warning": false, "grade": "B", "grade_label": "值得买入", "score": "58.8", "url": "https://www.28hse.com/en/buy/apartment/property-3919078", "source_label": "28Hse", "building_age": 27, "building_age_uncertain": false}, {"rank": 28, "estate": "冠德苑", "estate_zh": "冠德苑", "estate_display": "冠德苑", "district": "Ho Man Tin", "district_zh": "何文田", "district_display": "何文田", "region": "Kowloon", "region_zh": "九龙", "price_fmt": "HK$6.38M", "rent_fmt": "HK$33,711", "rent_note": "38 个租盘每呎租金平均 × 面积 · 同区（楼龄调整）", "rent_warning": false, "gross": "6.34%", "coc": "2.80%", "coc_stress": "1.74%", "ssd_warning": false, "grade": "B", "grade_label": "值得买入", "score": "58.7", "url": "https://www.28hse.com/en/buy/apartment/property-3808772", "source_label": "28Hse", "building_age": 6, "building_age_uncertain": true}, {"rank": 29, "estate": "东熹苑", "estate_zh": "东熹苑", "estate_display": "东熹苑", "district": "Sai Wan Ho", "district_zh": "西湾河", "district_display": "西湾河", "region": "Hong Kong Island", "region_zh": "港岛", "price_fmt": "HK$5.98M", "rent_fmt": "HK$33,670", "rent_note": "15 个租盘每呎租金平均 × 面积 · 同区（楼龄调整）", "rent_warning": false, "gross": "6.76%", "coc": "3.53%", "coc_stress": "2.47%", "ssd_warning": false, "grade": "B", "grade_label": "值得买入", "score": "58.3", "url": "https://www.28hse.com/en/buy/apartment/property-3908614", "source_label": "28Hse", "building_age": 31, "building_age_uncertain": false}, {"rank": 30, "estate": "西徑村", "estate_zh": "西徑村", "estate_display": "西徑村", "district": "Sai Kung", "district_zh": "西贡", "district_display": "西贡", "region": "New Territories", "region_zh": "新界", "price_fmt": "HK$13.80M", "rent_fmt": "HK$77,731", "rent_note": "25 个租盘每呎租金平均 × 面积 · 同区（楼龄调整）", "rent_warning": false, "gross": "6.76%", "coc": "3.35%", "coc_stress": "2.28%", "ssd_warning": false, "grade": "B", "grade_label": "值得买入", "score": "58.3", "url": "https://www.28hse.com/en/buy/apartment/property-3906501", "source_label": "28Hse", "building_age": 28, "building_age_uncertain": true}]